rainwaveclient/__init__.py
rainwaveclient/album.py
rainwaveclient/artist.py
rainwaveclient/category.py
rainwaveclient/channel.py
rainwaveclient/client.py
rainwaveclient/dispatch.py
rainwaveclient/listener.py
rainwaveclient/request.py
rainwaveclient/schedule.py
rainwaveclient/song.py
python_rainwave_client-2026.0.dist-info/WHEEL
python_rainwave_client-2026.0.dist-info/METADATA
python_rainwave_client-2026.0.dist-info/RECORD
